fluent/__init__.py
fluent/essential.py
fluent/launch.py
fluent/debug/__init__.py
fluent/debug/reload.py
fluent/render/__init__.py
fluent/render/font.py
fluent/render/property.py
fluent/render/window.py
fluent/widget/__init__.py
fluent/widget/core.py
fluent/widget/layout/__init__.py
fluent/widget/layout/align.py
fluent/widget/layout/overlay.py
fluent/widget/layout/padding.py
fluent/widget/layout/screen.py
fluent/widget/layout/spacer.py
fluent/widget/layout/stack.py
fluent/widget/shape/__init__.py
fluent/widget/shape/box.py
fluent/widget/shape/circle.py
fluent/widget/shape/text.py
libfluent-1.0.0b4.dist-info/METADATA
libfluent-1.0.0b4.dist-info/WHEEL
libfluent-1.0.0b4.dist-info/top_level.txt
libfluent-1.0.0b4.dist-info/RECORD
