Metadata-Version: 2.1
Name: libfluent
Version: 1.0.0b4
Summary: UNKNOWN
Home-page: https://github.com/libfluent/fluent
Author: Breitburg
Author-email: UNKNOWN
License: UNKNOWN
Platform: UNKNOWN
Classifier: Programming Language :: Python :: 3
Classifier: License :: OSI Approved :: MIT License
Classifier: Operating System :: OS Independent
Requires-Dist: pysdl2
Requires-Dist: reloadr
Requires-Dist: pyyaml
